vec_cluster/__init__.py
vec_cluster/cli.py
vec_cluster/core/__init__.py
vec_cluster/core/cluster.py
vec_cluster/core/data.py
vec_cluster/core/distance.py
vec_cluster/core/report.py
vec_cluster-0.2.2.dist-info/METADATA
vec_cluster-0.2.2.dist-info/WHEEL
vec_cluster-0.2.2.dist-info/entry_points.txt
vec_cluster-0.2.2.dist-info/top_level.txt
vec_cluster-0.2.2.dist-info/RECORD
