Metadata-Version: 2.4
Name: vec-cluster
Version: 0.2.2
Summary: Inspect and cluster generic vector features for entities
Author-email: mikewong23571 <mikewong23571@gmail.com>
License-Expression: MIT
Project-URL: Homepage, https://github.com/mikewong23571/vec-cluster
Project-URL: Repository, https://github.com/mikewong23571/vec-cluster
Project-URL: Issues, https://github.com/mikewong23571/vec-cluster/issues
Requires-Python: >=3.10
Requires-Dist: typer>=0.12.0
Requires-Dist: rich>=13.7.0
Requires-Dist: pandas>=2.0.0
Requires-Dist: numpy>=1.24.0
Requires-Dist: scikit-learn>=1.3.0
Requires-Dist: pyarrow>=15.0.0
